metaclock/__init__.py
metaclock/metaclock_combiner.py
metaclock/metaclock_mac.py
metaclock/metaclock_tailor.py
metaclock/metaclock_visualizer.py
metaclock/metaclock_configs/configs.json
metaclock/metaclock_configs/logging_config.ini
metaclock/utils/AlignStats.py
metaclock/utils/PreClock_LRM.py
metaclock/utils/SNP_rates.py
metaclock/utils/__init__.py
metaclock/utils/bo6_screen.py
metaclock/utils/data_types.py
metaclock/utils/filter.py
metaclock/utils/gff3_parser.py
metaclock/utils/metaclock_mac_template_configs.py
metaclock/utils/prokka_annotation.py
metaclock/utils/utils.py
metaclock-1.0.2.dist-info/LICENSE
metaclock-1.0.2.dist-info/METADATA
metaclock-1.0.2.dist-info/WHEEL
metaclock-1.0.2.dist-info/entry_points.txt
metaclock-1.0.2.dist-info/top_level.txt
metaclock-1.0.2.dist-info/RECORD
