Metadata-Version: 2.1
Name: metaclock
Version: 1.0.2
Summary: metaclock package test
Home-page: UNKNOWN
Author: Kun D. Huang
Author-email: kun.huang@unitn.it
License: A-GPL 3.0
Platform: UNKNOWN
Requires-Dist: biopython
Requires-Dist: matplotlib
Requires-Dist: numpy
Requires-Dist: pandas
Requires-Dist: seaborn
